moncashify/__init__.py
moncashify/constants.py
moncashify-0.3.0.dist-info/LICENSE
moncashify-0.3.0.dist-info/METADATA
moncashify-0.3.0.dist-info/WHEEL
moncashify-0.3.0.dist-info/top_level.txt
moncashify-0.3.0.dist-info/RECORD
