Metadata-Version: 2.1
Name: moncashify
Version: 0.3.0
Summary: Python SDK to make API requests and handle API responses from the MonCash API
Home-page: https://lemayzeur.github.io/moncashify_sdk
Author: Lub Lorry Lamysère
Author-email: lemayzeur@code9haiti.com
License: UNKNOWN
Platform: UNKNOWN
Classifier: Programming Language :: Python :: 3
Classifier: License :: OSI Approved :: MIT License
Classifier: Operating System :: OS Independent
Requires-Python: >=2.6, !=3.0.*, !=3.1.*, !=3.2.*, <4
